aliyunsdkccc/__init__.py
aliyunsdkccc/endpoint.py
aliyunsdkccc/request/__init__.py
aliyunsdkccc/request/v20200701/AbortCampaignRequest.py
aliyunsdkccc/request/v20200701/AddCasesRequest.py
aliyunsdkccc/request/v20200701/AddNumbersToSkillGroupRequest.py
aliyunsdkccc/request/v20200701/AddPersonalNumbersToUserRequest.py
aliyunsdkccc/request/v20200701/AddPhoneNumberToSkillGroupsRequest.py
aliyunsdkccc/request/v20200701/AddPhoneNumbersRequest.py
aliyunsdkccc/request/v20200701/AddSkillGroupsToUserRequest.py
aliyunsdkccc/request/v20200701/AddUsersToSkillGroupRequest.py
aliyunsdkccc/request/v20200701/AnswerCallRequest.py
aliyunsdkccc/request/v20200701/AppendCasesRequest.py
aliyunsdkccc/request/v20200701/AssignUsersRequest.py
aliyunsdkccc/request/v20200701/BargeInCallRequest.py
aliyunsdkccc/request/v20200701/BlindTransferRequest.py
aliyunsdkccc/request/v20200701/BridgeRtcCallRequest.py
aliyunsdkccc/request/v20200701/CancelAttendedTransferRequest.py
aliyunsdkccc/request/v20200701/ChangeWorkModeRequest.py
aliyunsdkccc/request/v20200701/CoachCallRequest.py
aliyunsdkccc/request/v20200701/CommitContactFlowRequest.py
aliyunsdkccc/request/v20200701/CompleteAttendedTransferRequest.py
aliyunsdkccc/request/v20200701/CreateAudioFileRequest.py
aliyunsdkccc/request/v20200701/CreateCallTagsRequest.py
aliyunsdkccc/request/v20200701/CreateCampaignRequest.py
aliyunsdkccc/request/v20200701/CreateContactFlowRequest.py
aliyunsdkccc/request/v20200701/CreateCustomCallTaggingRequest.py
aliyunsdkccc/request/v20200701/CreateInstanceRequest.py
aliyunsdkccc/request/v20200701/CreateSkillGroupRequest.py
aliyunsdkccc/request/v20200701/CreateUserRequest.py
aliyunsdkccc/request/v20200701/DeleteAudioFileRequest.py
aliyunsdkccc/request/v20200701/DeleteCallTagRequest.py
aliyunsdkccc/request/v20200701/DeleteContactFlowRequest.py
aliyunsdkccc/request/v20200701/DeleteCustomCallTaggingRequest.py
aliyunsdkccc/request/v20200701/DeleteSkillGroupRequest.py
aliyun_python_sdk_ccc-2.10.3.dist-info/LICENSE
aliyun_python_sdk_ccc-2.10.3.dist-info/METADATA
aliyun_python_sdk_ccc-2.10.3.dist-info/WHEEL
aliyun_python_sdk_ccc-2.10.3.dist-info/top_level.txt
aliyun_python_sdk_ccc-2.10.3.dist-info/RECORD
